{
  "_version     " : "PRA32-U Editor v3.1.0",
  "_comment     " : "  Current  #8   #9   #10  #11  #12  #13  #14  #15  ",
  "OSC_1_WAVE     " : [ [127], [127, 127, 127, 127, 127, 127, 127, 0  ] ],
  "OSC_1_SHAPE    " : [ [0  ], [0  , 0  , 0  , 0  , 0  , 0  , 0  , 0  ] ],
  "OSC_1_MORPH    " : [ [64 ], [64 , 64 , 64 , 64 , 64 , 0  , 0  , 0  ] ],
  "MIXER_SUB_OSC  " : [ [127], [127, 64 , 64 , 64 , 127, 127, 64 , 64 ] ],

  "OSC_2_WAVE     " : [ [0  ], [0  , 0  , 0  , 0  , 0  , 0  , 0  , 0  ] ],
  "OSC_2_COARSE   " : [ [64 ], [64 , 64 , 64 , 64 , 64 , 64 , 64 , 64 ] ],
  "OSC_2_PITCH    " : [ [109], [109, 72 , 72 , 72 , 72 , 72 , 72 , 72 ] ],
  "MIXER_OSC_MIX  " : [ [64 ], [64 , 64 , 64 , 64 , 64 , 64 , 64 , 0  ] ],

  "FILTER_CUTOFF  " : [ [115], [115, 115, 91 , 103, 55 , 115, 67 , 127] ],
  "FILTER_RESO    " : [ [64 ], [64 , 0  , 32 , 32 , 64 , 64 , 32 , 0  ] ],
  "FILTER_EG_AMT  " : [ [64 ], [64 , 64 , 88 , 16 , 112, 64 , 64 , 64 ] ],
  "FILTER_KEY_TRK " : [ [64 ], [64 , 64 , 64 , 64 , 64 , 64 , 64 , 0  ] ],

  "EG_ATTACK      " : [ [0  ], [0  , 64 , 48 , 96 , 0  , 0  , 0  , 0  ] ],
  "EG_DECAY       " : [ [0  ], [0  , 0  , 80 , 96 , 96 , 0  , 100, 0  ] ],
  "EG_SUSTAIN     " : [ [127], [127, 127, 0  , 0  , 0  , 127, 0  , 127] ],
  "EG_RELEASE     " : [ [0  ], [0  , 64 , 0  , 0  , 0  , 0  , 0  , 0  ] ],

  "EG_OSC_AMT     " : [ [64 ], [64 , 64 , 72 , 64 , 64 , 64 , 96 , 64 ] ],
  "EG_OSC_DST     " : [ [0  ], [0  , 0  , 64 , 0  , 0  , 0  , 127, 0  ] ],
  "VOICE_MODE     " : [ [127], [127, 0  , 0  , 0  , 75 , 127, 0  , 0  ] ],
  "PORTAMENTO     " : [ [0  ], [0  , 0  , 0  , 0  , 0  , 0  , 0  , 0  ] ],

  "LFO_WAVE       " : [ [0  ], [0  , 0  , 0  , 0  , 0  , 0  , 0  , 0  ] ],
  "LFO_RATE       " : [ [80 ], [80 , 80 , 80 , 80 , 80 , 80 , 80 , 80 ] ],
  "LFO_DEPTH      " : [ [0  ], [0  , 0  , 0  , 0  , 0  , 127, 0  , 0  ] ],
  "LFO_FADE_TIME  " : [ [0  ], [0  , 0  , 0  , 0  , 0  , 0  , 0  , 0  ] ],

  "LFO_OSC_AMT    " : [ [96 ], [96 , 96 , 64 , 64 , 64 , 96 , 64 , 64 ] ],
  "LFO_OSC_DST    " : [ [0  ], [0  , 0  , 0  , 0  , 0  , 127, 0  , 0  ] ],
  "LFO_FILTER_AMT " : [ [64 ], [64 , 64 , 88 , 88 , 88 , 64 , 88 , 64 ] ],
  "AMP_GAIN       " : [ [90 ], [90 , 90 , 90 , 90 , 90 , 90 , 127, 90 ] ],

  "AMP_ATTACK     " : [ [0  ], [0  , 0  , 0  , 0  , 0  , 0  , 0  , 0  ] ],
  "AMP_DECAY      " : [ [0  ], [0  , 0  , 0  , 0  , 0  , 0  , 0  , 0  ] ],
  "AMP_SUSTAIN    " : [ [127], [127, 127, 127, 127, 127, 127, 127, 127] ],
  "AMP_RELEASE    " : [ [0  ], [0  , 0  , 0  , 0  , 0  , 0  , 0  , 0  ] ],

  "FILTER_MODE    " : [ [0  ], [0  , 0  , 0  , 0  , 0  , 0  , 0  , 0  ] ],
  "EG_AMP_MOD     " : [ [127], [127, 127, 0  , 0  , 127, 127, 127, 0  ] ],
  "REL_EQ_DECAY   " : [ [0  ], [0  , 0  , 0  , 0  , 127, 0  , 0  , 0  ] ],
  "P_BEND_RANGE   " : [ [12 ], [12 , 12 , 12 , 12 , 12 , 12 , 12 , 12 ] ],

  "BTH_FILTER_AMT " : [ [64 ], [64 , 64 , 64 , 64 , 64 , 64 , 64 , 64 ] ],
  "BTH_AMP_MOD    " : [ [0  ], [0  , 0  , 0  , 0  , 0  , 0  , 0  , 0  ] ],
  "EG_VEL_SENS    " : [ [0  ], [0  , 0  , 0  , 0  , 0  , 0  , 0  , 0  ] ],
  "AMP_VEL_SENS   " : [ [0  ], [0  , 0  , 0  , 0  , 0  , 0  , 0  , 0  ] ],

  "VOICE_ASGN_MODE" : [ [0  ], [0  , 0  , 0  , 0  , 0  , 0  , 0  , 0  ] ],




  "CHORUS_MIX     " : [ [64 ], [64 , 127, 127, 127, 64 , 64 , 127, 0  ] ],
  "CHORUS_RATE    " : [ [64 ], [64 , 64 , 64 , 64 , 64 , 64 , 64 , 64 ] ],
  "CHORUS_DEPTH   " : [ [64 ], [64 , 64 , 64 , 64 , 64 , 64 , 64 , 64 ] ],


  "DELAY_FEEDBACK " : [ [64 ], [64 , 64 , 64 , 64 , 64 , 64 , 64 , 0  ] ],
  "DELAY_TIME     " : [ [93 ], [93 , 93 , 93 , 93 , 93 , 93 , 93 , 93 ] ],
  "DELAY_MODE     " : [ [0  ], [0  , 0  , 0  , 0  , 0  , 0  , 0  , 0  ] ],

  "_end         " : ""
}
